LICENSE
README.md
setup.cfg
setup.py
tpunicorn/__init__.py
tpunicorn/_version.py
tpunicorn/program.py
tpunicorn/serve.py
tpunicorn/tpu.py
tpunicorn.egg-info/PKG-INFO
tpunicorn.egg-info/SOURCES.txt
tpunicorn.egg-info/dependency_links.txt
tpunicorn.egg-info/entry_points.txt
tpunicorn.egg-info/requires.txt
tpunicorn.egg-info/top_level.txt